{
  "Index": {
    "title": "ԱԻՆ ԿՏԱՆԻ ԻՄ ԱՇԽԱՏԱՆՔԸ:",
    "placeholder": "Մուտքագրեք ձեր մասնագիտությունը (օրինակ՝ ծրագրավորող)",
    "button": "Ստուգեք ապագան",
    "loading": "Վերլուծելով...",
    "risk_label": "Ավտոմատացման վտանգ",
    "skills_label": "Անվտանգ հմտություններ",
    "tasks_label": "Վտանգված առաջադրանքներ",
    "verdict": "Դատավճիռ",
    "reasoning": "Հիմնավորում",
    "meta_title": "Արդյո՞ք AI-ն կվերցնի իմ աշխատանքը: - Անվճար կարիերայի վերլուծություն",
    "meta_description": "Ստուգեք, արդյոք արհեստական ​​ինտելեկտը վտանգ է ներկայացնում ձեր մասնագիտության համար: Ստացեք անվճար ռիսկերի վերլուծություն և անվտանգ հմտությունների ցանկ:"
  },
  "Footer": {
    "powered_by": "Աջակցում է",
    "community": "Միացեք համայնքին",
    "statistics": "Վիճակագրություն"
  }
}